<?xml version="1.0" encoding="UTF-8"?>
<?xml-model href="dhd.rnc" type="application/relax-ng-compact-syntax"?>
<text id="dhdmtr0145"><p>我<說咒者>漚波羅龍王</說咒者>今欲說神呪。名<咒名>伊提姤摩</咒名>。晉言稱眾生心不違其意。譬如大海七珍具足。取者皆得。其不取者非龍王咎。<咒語>烏都胡盧都　支波都　宿佉都　耆摩都　烏吒都　若蜜耆都　畢梨帝那都　烏蘇都　莎呵</咒語></p>
<p><施咒法>誦呪三遍<物品>縷紅白二色結</物品>作八結繫項。</施咒法>
此大神呪。乃是過去二十恒河沙諸佛所說。我從諸佛得此陀羅尼。從是已來百阿僧祇劫。有大神力神通自在。遊騰十方歷事諸佛。常以愛語軟語。利益同事調伏眾生。於諸眾生猶如慈父。心意寬弘猶如大海。含受眾生無所不苞。堪任荷負無量重擔。愍苦眾生施其安隱。</p>
<p><使用方法><功效>若諸眾生來求索者。隨其所願不逆其意。<益處>求官職者令得職爵</益處>。<益處>求大富者施其寶藏</益處>。<症狀>疾病者</症狀>施其安隱。若諸國王欲求所願。我悉與之不違其意。<益處>求長壽與長壽</益處>。欲令<益處 t ="國土危難">國土無災害</益處>。<益處 t ="風調雨順">雨澤時節不旱不澇。正得其中無諸災霜</益處>。<益處 t ="風調雨順">穀米豐熟</益處>人民安樂。<益處 t ="疫病">疫毒不行</益處>。<益處 t ="滿願">滿其所願終不違意</益處>。</功效><施咒法>是王爾時復能讀誦上來所說陀羅尼句。兼以十善化諸人民。如我上說所修功德。其王亦應如是修行。修行得已兼復讀誦此陀羅尼。</施咒法>曩劫所作極重惡業。皆悉消滅無有遺餘。</使用方法></p>

<p><使用方法>是王爾時罪垢滅已。其心泰然無眾惱患。怨憎平等無有親愛。<施咒法>常以月<時間 t="pt">八日</時間><時間 t="pt">十四日</時間><時間 t="pt">十五日</時間>沐浴受齋。於<時間 t="pt">清旦時日</時間>王未出。若正殿上若高樓上。正東而坐。七遍誦此陀羅尼呪。燒<物品>白栴檀</物品>及<物品>沈水香</物品>。散<物品>七色華</物品>供養十方佛已。爾時應當三稱我名漚波羅龍王滿我所願。如是三說。即尋誦此陀羅尼句七遍乃止。</施咒法>是王爾時已精誠故。十方諸佛諸大菩薩。釋梵四天王八大龍王。我漚波羅龍王。以慈悲蓋覆其國土。以甘露水灑其國界。<功效>令其疾病疾毒惡氣悉得消滅。</功效>是名大神呪力滿願不虛。</使用方法></p></text> 

