<?xml version="1.0" encoding="UTF-8"?>
<?xml-model href="dhd.rnc" type="application/relax-ng-compact-syntax"?>
<text id="dhdmtr0280">
<p><使用方法><方法名稱>央俱施口法印第三十五</方法名稱> (丹第十七誦後大呪)
    <施咒法><手印  t="口法印">以左右小指。內雙直竪右無名指。㧙在左無名及中指背已。即向頭指中指岐間入。又以左無名指。從右中指無名指岐間出之。即入食指中指間。二中指直竪頭相拄。二食指各屈。鉤無名指頭。並二大指。直竪頭相拄。與二小指相離半寸許。</手印 ></施咒法>
    是一法印。<功效><症狀  r="邪魅病">制伏一切鬼神言語妄說諂曲</症狀>。<施咒法>作此印已誦後大呪。</施咒法>更不敢語神病即差。</功效></使用方法></p>

<p><使用方法><方法名稱>央俱施牙法印第三十六</方法名稱> (丹第十八亦名急縛鬼印)
<施咒法><手印  t="牙法印">竝竪二小指頭相著。反叉二無名指。在於掌中右押左。頭向虎口出。竝竪二中指頭相著各。㧙二頭指。在中指背上。頭當第三節捻之竝竪二大指合腕。</手印 ></施咒法>
是一法印。<功效>有人病患。所有痛處。<施咒法>當作此印誦後大呪。以印痛處</施咒法>其病即差。</功效></使用方法></p>

<p><使用方法><方法名稱>央俱施索法印第三十八</方法名稱> (丹第二十誦後大呪)
<施咒法><手印  t="索法印">二手掌相背著。以二無名指相交。申之如繩。二中指亦爾。二小指各屈如鉤。又各屈二大指。更屈二頭指。各鉤二大指上。狀如鉤形</手印 ></施咒法>
是一法印。<功效>若有鬼神。心生違逆不從佛法者。<施咒法>先應用前鉤印喚來。來已即當作此印法誦後大呪。縛之勘問。</施咒法>鬼神皆伏不敢縱暴是法大驗。</功效></使用方法></p>


<咒名>央俱施療病法印大呪第四十</咒名>(丹第二十二亦名縛鬼印誦後大呪)
<p><使用方法><施咒法><手印  t="療病法印">准前身印。上唯改二頭指。各當中指第二節前文。著之。又各屈二大指頭。入掌中合腕</手印 ></施咒法>
是一法印。<功效>若欲降伏一切鬼神。及欲療治一切病者。</功效><施咒法>當作此印印其病處。誦後大呪七遍。即差。</施咒法></使用方法></p>

<p>央俱施大呪呪曰。<咒語>那(上音)謨(上音)囉(上音)怛那(二合)跢囉(二合)夜耶(一)那謨(同上)室旃(二合)茶跋折囉波拏曳(二)摩訶藥叉栖那波跢曳(三)唵(四)跋折囉央俱施(五)迦比羅雞施(六)跢智跢智(七)遮智遮智(八)麁智母智儞(九)迦嚧迦(上音)知(十)摩嚧迦(上音)知(十一)武知跋折唎(十二)摩訶毘住嚕例(十三)豆鳩豆鳩(十四)素武素武(十五)素嚕素嚕(十六)娑囉娑囉(十七)毘娑囉毘娑囉(十八)嗚𤙖嗚𤙖(十九)嗚𤙖嗚𤙖(二十)泮泮泮泮(二十一)欝住呼(二合)遲羝(二十二)訶羅訶羅(二十三)憑(比應反)伽(去音)例(二十四)遮智毘遮智(二十五)娑婆(去音)羅(二十六)毘狄(去音)例薩婆地婆那(去音)伽(二十七)波囉(二合)訶囉(去音)那(二十八)麼夜三麼地(二十九)𠼝地(二合)陀翼計治(二合下同三十)素狼(去音)計冶(二合)(三十一)俱狼(去音)計治(二合)(三十二)跋折囉胡泥(上音三十三)跋折囉遲唎馱娑(上音)羅波羅訶囉(上音)若(若冶反三十四)囉(上音)怛那(二合)跢囉(二合)夜地(三十五)羯囉(二合)磨致唎(二合)[怡-台+孚]羝(三十六)跋折囉陀(去音)囉(三十七)毘濕婆(二合)娑(上音)儞(三十八)阿跋囉智訶(上音)跢(上音三十九)跋囉摩囉(二合)陀(去音)儞(四十)跋折囉央俱施(四十一)阿怛若(二合)波夜底(四十二)莎訶(四十三)</咒語></p>

<p><使用方法><施咒法>是大法呪。異常操烈。不可卒誦。</施咒法><功效>療病至驗。</功效></使用方法>

<使用方法><施咒法>若有人能受持者。必須淨身。護持戒行。無至染著。遠離塵俗及諸穢污一切雜思。若能如是護持行者。當於<時間 t="f">日日</時間>香湯洗浴著新淨衣。入道場中。燒<物品>安悉香</物品>及種種<物品>物</物品>。<物品>飲食</物品>供養結界護身。<時間 t="f">七日七夜</時間>誦是呪。滿十萬遍已。然後更入金剛受法壇竟。於後用法療病之時。當立<物品>水壇</物品>。燒<物品>安悉香</物品>。多少<物品>飲食</物品>而供養已。作印誦呪</施咒法><功效>療病即差。</功效></使用方法>

<使用方法><施咒法>若呪師向鬼病人邊。正到之時。鬼避去者。呪師即立地。作前央俱施身印。喚其鬼神近著治之。</施咒法><功效>其病即差。</功效></使用方法></p></text>
